Minuit_newClass/__init__.py
Minuit_newClass/extendedMinuit.py
Minuit_Extension-0.1.0.dist-info/METADATA
Minuit_Extension-0.1.0.dist-info/WHEEL
Minuit_Extension-0.1.0.dist-info/top_level.txt
Minuit_Extension-0.1.0.dist-info/RECORD
