Metadata-Version: 2.1
Name: Minuit-Extension
Version: 0.1.0
Summary: Extension library for Minuit Class
Home-page: UNKNOWN
Author: Yehan Edirisinghe
Author-email: yehan278@gmail.com
License: None
Platform: UNKNOWN
Classifier: Intended Audience :: Developers
Classifier: Programming Language :: Python
Classifier: Programming Language :: Python :: 3
Classifier: Programming Language :: Python :: 3.6
Classifier: Programming Language :: Python :: 3.7
Classifier: Programming Language :: Python :: 3.8
Classifier: Programming Language :: Python :: 3.9
Classifier: Operating System :: OS Independent
Requires-Dist: iminuit
Requires-Dist: sympy
